{
  "insert-template": [
    {
      "modifiers": [
        "Alt"
      ],
      "key": "T"
    }
  ],
  "app:go-back": [
    {
      "modifiers": [
        "Mod",
        "Alt"
      ],
      "key": "ArrowLeft"
    },
    {
      "modifiers": [
        "Alt"
      ],
      "key": "ArrowLeft"
    }
  ],
  "app:go-forward": [
    {
      "modifiers": [
        "Mod",
        "Alt"
      ],
      "key": "ArrowRight"
    },
    {
      "modifiers": [
        "Alt"
      ],
      "key": "ArrowRight"
    }
  ],
  "editor:swap-line-up": [
    {
      "modifiers": [
        "Mod"
      ],
      "key": "P"
    }
  ],
  "editor:swap-line-down": [
    {
      "modifiers": [
        "Mod"
      ],
      "key": "N"
    }
  ],
  "colored-text:color-text": [
    {
      "modifiers": [
        "Alt",
        "Mod"
      ],
      "key": "H"
    }
  ]
}